{
  "index" : {
    "title"       : "test",
    "breadcrumb"  : "HOME",
    "description" : "test",
    "keywords"    : "",
    "body_id"     : "index"
  },

  "company" : {
    "index"  : {
      "title"       : "test1 | test",
      "breadcrumb"  : "TEST1",
      "description" : "test1",
      "keywords"    : "",
      "body_id"     : "company_index"
    },

    "detail" : {
      "index"  : {
        "title"       : "test1_1 | test1 | test",
        "breadcrumb"  : "TEST1_1",
        "description" : "test1_1",
        "keywords"    : "",
        "body_id"     : "company_detial"
      }
    }
  }
}
